.gitignore
.travis.yml
CHANGES.rst
Dockerfile
MANIFEST.in
Makefile
README.rst
TODO.txt
bootstrap.py
buildout.cfg
develop-noproxy.ini
develop.ini
docker-compose.yml
docker-entrypoint.sh
requirements.txt
setup.py
.github/workflows/codeql-analysis.yml
docs/about.rst
docs/conf.py
docs/config.rst
docs/index.rst
docs/install.rst
docs/users.rst
docs/webserverplugins.rst
factored/__init__.py
factored/app.py
factored/auth_tkt.py
factored/finders.py
factored/models.py
factored/plugins.py
factored/request.py
factored/sm.py
factored/sql.py
factored/subscribers.py
factored/templates.py
factored/utils.py
factored/views.py
factored.egg-info/PKG-INFO
factored.egg-info/SOURCES.txt
factored.egg-info/dependency_links.txt
factored.egg-info/entry_points.txt
factored.egg-info/not-zip-safe
factored.egg-info/requires.txt
factored.egg-info/top_level.txt
factored/scripts/__init__.py
factored/scripts/fakesmtp.py
factored/scripts/initializedb.py
factored/scripts/users.py
factored/static/poweredby_wildcard.png
factored/static/bootstrap/css/bootstrap.css
factored/static/bootstrap/css/bootstrap.css.map
factored/static/bootstrap/css/bootstrap.min.css
factored/static/bootstrap/fonts/glyphicons-halflings-regular.eot
factored/static/bootstrap/fonts/glyphicons-halflings-regular.svg
factored/static/bootstrap/fonts/glyphicons-halflings-regular.ttf
factored/static/bootstrap/fonts/glyphicons-halflings-regular.woff
factored/static/bootstrap/js/bootstrap.js
factored/static/bootstrap/js/bootstrap.min.js
factored/templates/auth-chooser.pt
factored/templates/auth-code.pt
factored/templates/auth-controls.pt
factored/templates/auth-email.pt
factored/templates/auth.pt
factored/templates/footer.pt
factored/templates/includes.pt
factored/templates/layout.pt
factored/templates/meta.pt
factored/templates/title.pt
factored/tests/__init__.py
factored/tests/test_auth.py
plugins/README.txt
plugins/ats.lua
plugins/bit.lua
plugins/factored.lua
plugins/nginx.lua
plugins/sha.lua
plugins/shaold.lua