Metadata-Version: 2.1
Name: factored
Version: 4.1.0
Summary: A WSGI app that allows you to add another factor of authentication to any application server.
Home-page: https://github.com/wildcardcorp/factored
Author: Nathan Van Gheem
Author-email: vangheem@gmail.com
License: GPL2
Keywords: mutli factor authentication 2factor mutl-factor auth auth_tkt google otp
Platform: UNKNOWN
Classifier: Topic :: Internet :: WWW/HTTP :: WSGI
Classifier: Topic :: Internet :: WWW/HTTP :: WSGI :: Application
Classifier: Topic :: Internet :: WWW/HTTP :: WSGI :: Middleware
Provides-Extra: test
Provides-Extra: proxy
